try_match/__init__.py
try_match/_try_match.py
try_match-0.2.0.dist-info/LICENSE
try_match-0.2.0.dist-info/WHEEL
try_match-0.2.0.dist-info/METADATA
try_match-0.2.0.dist-info/RECORD
