Metadata-Version: 2.1
Name: try-match
Version: 0.2.0
Summary: Pattern matching
Home-page: https://github.com/zen-xu/try_match
License: Apache-2.0
Keywords: pattern matching,switch,exception
Author: Zhengyu Xu
Author-email: zen-xu@outlook.com
Requires-Python: >=2.7,<4
Classifier: Intended Audience :: Developers
Classifier: License :: OSI Approved :: Apache Software License
Classifier: Operating System :: OS Independent
Classifier: Programming Language :: Python
Classifier: Programming Language :: Python :: 2
Classifier: Programming Language :: Python :: 2.7
Classifier: Programming Language :: Python :: 3
Classifier: Programming Language :: Python :: 3.4
Classifier: Programming Language :: Python :: 3.5
Classifier: Programming Language :: Python :: 3.6
Classifier: Programming Language :: Python :: 3.7
Project-URL: Repository, https://github.com/zen-xu/try_match
